dismantler/__init__.py
dismantler/__version__.py
dismantler/api.py
dismantler/dismantler.py
dismantler/exceptions.py
dismantler/models.py
dismantler_python-0.0.2.dist-info/METADATA
dismantler_python-0.0.2.dist-info/RECORD
dismantler_python-0.0.2.dist-info/WHEEL
dismantler_python-0.0.2.dist-info/top_level.txt
